{
	"configurations" : 
	[
		{
			"directories" : 
			[
				{
					"build" : ".",
					"jsonFile" : "directory-.-Debug-f5ebdc15457944623624.json",
					"minimumCMakeVersion" : 
					{
						"string" : "3.26"
					},
					"projectIndex" : 0,
					"source" : ".",
					"targetIndexes" : 
					[
						0
					]
				}
			],
			"name" : "Debug",
			"projects" : 
			[
				{
					"directoryIndexes" : 
					[
						0
					],
					"name" : "exemplo04b",
					"targetIndexes" : 
					[
						0
					]
				}
			],
			"targets" : 
			[
				{
					"directoryIndex" : 0,
					"id" : "exemplo04b::@6890427a1f51a3e7e1df",
					"jsonFile" : "target-exemplo04b-Debug-260e5949a92be9ef628e.json",
					"name" : "exemplo04b",
					"projectIndex" : 0
				}
			]
		}
	],
	"kind" : "codemodel",
	"paths" : 
	{
		"build" : "/Users/marcosmoraes/lpnoite/aula2402/exemplo04b/cmake-build-debug",
		"source" : "/Users/marcosmoraes/lpnoite/aula2402/exemplo04b"
	},
	"version" : 
	{
		"major" : 2,
		"minor" : 5
	}
}
